ReadWord/__init__.py
ReadWord/readword.py
ReadWord-0.0.5.dist-info/LICENSE.txt
ReadWord-0.0.5.dist-info/METADATA
ReadWord-0.0.5.dist-info/WHEEL
ReadWord-0.0.5.dist-info/top_level.txt
ReadWord-0.0.5.dist-info/RECORD
