Metadata-Version: 2.1
Name: ReadWord
Version: 0.0.5
Summary: 快速读取docx文档内容
Home-page: 
Author: 测码范晔
Author-email: 1538379200@qq.com
License: UNKNOWN
Platform: UNKNOWN
Classifier: Programming Language :: Python :: 3
Classifier: License :: OSI Approved :: MIT License
Classifier: Operating System :: OS Independent
License-File: LICENSE.txt
Requires-Dist: bs4
